setup.py
Openkst.egg-info/PKG-INFO
Openkst.egg-info/SOURCES.txt
Openkst.egg-info/dependency_links.txt
Openkst.egg-info/requires.txt
Openkst.egg-info/top_level.txt
Text_Entity/__init__.py
Text_Entity/text_entity.py
Text_Entity/openks/__init__.py
Text_Entity/openks/abstract/__init__.py
Text_Entity/openks/abstract/mmd.py
Text_Entity/openks/abstract/mtg.py
Text_Entity/openks/common/__init__.py
Text_Entity/openks/common/register.py
Text_Entity/openks/distributed/__init__.py
Text_Entity/openks/distributed/cloud_utils.py
Text_Entity/openks/distributed/datafeeder.py
Text_Entity/openks/distributed/openKS_CPU_test.py
Text_Entity/openks/distributed/openKS_GPU_test.py
Text_Entity/openks/distributed/openks_launcher.py
Text_Entity/openks/distributed/utils.py
Text_Entity/openks/distributed/openks_distributed/__init__.py
Text_Entity/openks/distributed/openks_distributed/base/BaseDistributed.py
Text_Entity/openks/distributed/openks_distributed/base/RoleMaker.py
Text_Entity/openks/distributed/openks_distributed/base/__init__.py
Text_Entity/openks/distributed/openks_distributed/base/mode.py
Text_Entity/openks/distributed/openks_distributed/cpu/CPUDistributed.py
Text_Entity/openks/distributed/openks_distributed/cpu/__init__.py
Text_Entity/openks/distributed/openks_distributed/gpu/GPUDistributed.py
Text_Entity/openks/distributed/openks_distributed/gpu/__init__.py
Text_Entity/openks/distributed/openks_distributed/gpu/fs_wrapper.py
Text_Entity/openks/distributed/openks_graphlearning/__init__.py
Text_Entity/openks/distributed/openks_graphlearning/openks_graph.py
Text_Entity/openks/distributed/openks_graphlearning/openks_graph_wrapper.py
Text_Entity/openks/distributed/openks_strategy/__init__.py
Text_Entity/openks/distributed/openks_strategy/base.py
Text_Entity/openks/distributed/openks_strategy/cpu.py
Text_Entity/openks/distributed/openks_strategy/gpu.py
Text_Entity/openks/distributed/quick-start/KsPyReader.py
Text_Entity/openks/distributed/quick-start/KsPyReader2.py
Text_Entity/openks/distributed/quick-start/KsPyReader_test.py
Text_Entity/openks/distributed/quick-start/__init__.py
